[
  {
    "name": "יוסף אבו גויעד",
    "idNumber": "21519392",
    "phone": "054-289-6709",
    "coordinationNumber": "22",
    "goodsType": "סלי מזון",
    "donorOrg": "GHF",
    "palletCount": "22",
    "passedAt": "14:29",
    "gatePassPrinted": true
  },
  {
    "name": "עודד צפרירי",
    "idNumber": "22621577",
    "phone": "050-726-9220",
    "coordinationNumber": "66",
    "goodsType": "סלי מזון",
    "donorOrg": "GHF",
    "palletCount": "22",
    "passedAt": "13:48",
    "gatePassPrinted": true
  },
  {
    "name": "אבו עבד חאלד",
    "idNumber": "23296270",
    "phone": "052-243-1181",
    "coordinationNumber": "1",
    "goodsType": "סלי מזון",
    "donorOrg": "GHF",
    "palletCount": "22",
    "passedAt": "10:37",
    "gatePassPrinted": true
  },
  {
    "name": "חוסאם נג'אר",
    "idNumber": "23341159",
    "phone": "050-526-6718",
    "coordinationNumber": "53",
    "goodsType": "מארזי מזון",
    "donorOrg": "GHF",
    "palletCount": "22",
    "passedAt": "11:29",
    "gatePassPrinted": true
  },
  {
    "name": "עופר מטודי",
    "idNumber": "24398455",
    "phone": "050-453-8884",
    "coordinationNumber": "96",
    "goodsType": "קמח - WFP",
    "donorOrg": "WFP",
    "palletCount": "18",
    "passedAt": "06:48",
    "gatePassPrinted": true
  },
  {
    "name": "דורון יחיא",
    "idNumber": "24803942",
    "phone": "058-726-5502",
    "coordinationNumber": "16",
    "goodsType": "מארזי מזון",
    "donorOrg": "GHF",
    "palletCount": "22",
    "passedAt": "12:11",
    "gatePassPrinted": true
  },
  {
    "name": "דורון יחיא",
    "idNumber": "24803942",
    "phone": "058-726-5502",
    "coordinationNumber": "94",
    "goodsType": "קמח - WFP",
    "donorOrg": "WFP",
    "palletCount": "18",
    "passedAt": "07:28",
    "gatePassPrinted": true
  },
  {
    "name": "שי סמין",
    "idNumber": "25240649",
    "phone": "054-566-0744",
    "coordinationNumber": "93",
    "goodsType": "קמח - WFP",
    "donorOrg": "WFP",
    "palletCount": "18",
    "passedAt": "07:23",
    "gatePassPrinted": true
  },
  {
    "name": "אלחוגר טאלב",
    "idNumber": "26210500",
    "phone": "",
    "coordinationNumber": "64",
    "goodsType": "מארזי מזון",
    "donorOrg": "GHF",
    "palletCount": "22",
    "passedAt": "13:44",
    "gatePassPrinted": true
  },
  {
    "name": "איאד שיבלי",
    "idNumber": "25990680",
    "phone": "052-700-1237",
    "coordinationNumber": "59",
    "goodsType": "מארזי מזון",
    "donorOrg": "GHF",
    "palletCount": "22",
    "passedAt": "11:34",
    "gatePassPrinted": true
  },
  {
    "name": "עודה אלמחדי",
    "idNumber": "26132316",
    "phone": "",
    "coordinationNumber": "61",
    "goodsType": "סלי מזון ",
    "donorOrg": "GHF",
    "palletCount": "22",
    "passedAt": "11:32",
    "gatePassPrinted": true
  },
  {
    "name": "סלמאן אלמערז",
    "idNumber": "26137000",
    "phone": "054-938-0578",
    "coordinationNumber": "4",
    "goodsType": "סלי מזון",
    "donorOrg": "GHF",
    "palletCount": "22",
    "passedAt": "09:35",
    "gatePassPrinted": true
  },
  {
    "name": "עטיה אלמחדי",
    "idNumber": "26215640",
    "phone": "",
    "coordinationNumber": "63",
    "goodsType": "מארזי מזון",
    "donorOrg": "GHF",
    "palletCount": "22",
    "passedAt": "13:50",
    "gatePassPrinted": true
  },
  {
    "name": "אסמאעיל רבידיאן",
    "idNumber": "308325943",
    "phone": "",
    "coordinationNumber": "51",
    "goodsType": "מארזי מזון",
    "donorOrg": "GHF",
    "palletCount": "22",
    "passedAt": "14:20",
    "gatePassPrinted": true
  },
  {
    "name": "דן אהרונוביץ'",
    "idNumber": "28091494",
    "phone": "052-537-4201",
    "coordinationNumber": "9",
    "goodsType": "סלי מזון ",
    "donorOrg": "GHF",
    "palletCount": "22",
    "passedAt": "09:39",
    "gatePassPrinted": true
  },
  {
    "name": "דן אהרונוביץ'",
    "idNumber": "28091494",
    "phone": "052-537-4201",
    "coordinationNumber": "91",
    "goodsType": "קמח - WFP",
    "donorOrg": "WFP",
    "palletCount": "18",
    "passedAt": "13:24",
    "gatePassPrinted": false
  },
  {
    "name": "ראיף אכתילאת",
    "idNumber": "028161016",
    "phone": "053-964-1089",
    "coordinationNumber": "77",
    "goodsType": "ציוד רפואי מתכלה",
    "donorOrg": "MSF",
    "palletCount": "15",
    "passedAt": "08:08",
    "gatePassPrinted": true
  },
  {
    "name": "מוחמד יוסף אבו נאיף",
    "idNumber": "28211167",
    "phone": "052-355-0102",
    "coordinationNumber": "31",
    "goodsType": "סלי מזון",
    "donorOrg": "GHF",
    "palletCount": "22",
    "passedAt": "14:23",
    "gatePassPrinted": true
  },
  {
    "name": "יונס אבו פרחה",
    "idNumber": "28332351",
    "phone": "050-895-4857",
    "coordinationNumber": "57",
    "goodsType": "מארזי מזון",
    "donorOrg": "GHF",
    "palletCount": "22",
    "passedAt": "13:41",
    "gatePassPrinted": true
  },
  {
    "name": "רונן בן דוד",
    "idNumber": "28844157",
    "phone": "050-939-3144",
    "coordinationNumber": "82",
    "goodsType": "מזון",
    "donorOrg": "WCK",
    "palletCount": "22",
    "passedAt": "07:21",
    "gatePassPrinted": true
  },
  {
    "name": "ג'מל אלגרנאואי",
    "idNumber": "29855608",
    "phone": "053-272-1810",
    "coordinationNumber": "80",
    "goodsType": "שימורים - WCK",
    "donorOrg": "WCK",
    "palletCount": "22",
    "passedAt": "07:24",
    "gatePassPrinted": true
  },
  {
    "name": "אלגבור יוסף",
    "idNumber": "29859451",
    "phone": "052-920-5172",
    "coordinationNumber": "92",
    "goodsType": "קמח - WFP",
    "donorOrg": "WFP",
    "palletCount": "18",
    "passedAt": "06:23",
    "gatePassPrinted": true
  },
  {
    "name": "חאלד עמאדין",
    "idNumber": "029953197",
    "phone": "053-728-4456",
    "coordinationNumber": "47",
    "goodsType": "סלי מזון",
    "donorOrg": "GHF",
    "palletCount": "22",
    "passedAt": "14:11",
    "gatePassPrinted": true
  },
  {
    "name": "מכלוף ליאור",
    "idNumber": "31509276",
    "phone": "054-311-2878",
    "coordinationNumber": "5",
    "goodsType": "סלי מזון",
    "donorOrg": "GHF",
    "palletCount": "22",
    "passedAt": "09:58",
    "gatePassPrinted": true
  },
  {
    "name": "טלאל אלקרינאוי",
    "idNumber": "31517709",
    "phone": "052-743-1124",
    "coordinationNumber": "55",
    "goodsType": "מארזי מזון",
    "donorOrg": "GHF",
    "palletCount": "22",
    "passedAt": "13:46",
    "gatePassPrinted": true
  },
  {
    "name": "נאיל לחאם",
    "idNumber": "43066695",
    "phone": "054-767-0225",
    "coordinationNumber": "42",
    "goodsType": "סלי מזון",
    "donorOrg": "GHF",
    "palletCount": "22",
    "passedAt": "14:04",
    "gatePassPrinted": true
  },
  {
    "name": "שמסי סעאידה",
    "idNumber": "33909136",
    "phone": "050-433-5723",
    "coordinationNumber": "44",
    "goodsType": "סלי מזון",
    "donorOrg": "GHF",
    "palletCount": "22",
    "passedAt": "14:06",
    "gatePassPrinted": true
  },
  {
    "name": "וליד בדיר",
    "idNumber": "34247379",
    "phone": "052-628-2210",
    "coordinationNumber": "36",
    "goodsType": "מארזי מזון",
    "donorOrg": "GHF",
    "palletCount": "22",
    "passedAt": "14:16",
    "gatePassPrinted": true
  },
  {
    "name": "אחמד אזברגה",
    "idNumber": "37286325",
    "phone": "050-532-2250",
    "coordinationNumber": "68",
    "goodsType": "מארזי מזון",
    "donorOrg": "GHF",
    "palletCount": "22",
    "passedAt": "11:28",
    "gatePassPrinted": true
  },
  {
    "name": "אפיק נגר",
    "idNumber": "37969896",
    "phone": "050-633-6078",
    "coordinationNumber": "89",
    "goodsType": "קמח - WFP",
    "donorOrg": "WFP",
    "palletCount": "18",
    "passedAt": "07:57",
    "gatePassPrinted": true
  },
  {
    "name": "ארסן אלסייד",
    "idNumber": "39234273",
    "phone": "050-668-1866",
    "coordinationNumber": "8",
    "goodsType": "סלי מזון",
    "donorOrg": "GHF",
    "palletCount": "22",
    "passedAt": "11:19",
    "gatePassPrinted": true
  },
  {
    "name": "גאלב אלעביד",
    "idNumber": "39347828",
    "phone": "052-319-9965",
    "coordinationNumber": "50",
    "goodsType": "מזון",
    "donorOrg": "GHF",
    "palletCount": "22",
    "passedAt": "13:44",
    "gatePassPrinted": true
  },
  {
    "name": "מחמד טוויל",
    "idNumber": "41001041",
    "phone": "052-703-8064",
    "coordinationNumber": "86",
    "goodsType": "קמח - WFP",
    "donorOrg": "WFP",
    "palletCount": "18",
    "passedAt": "06:22",
    "gatePassPrinted": true
  },
  {
    "name": "ציון בואהרון",
    "idNumber": "53205936",
    "phone": "054-207-9040",
    "coordinationNumber": "12",
    "goodsType": "מארזי מזון",
    "donorOrg": "GHF",
    "palletCount": "22",
    "passedAt": "11:28",
    "gatePassPrinted": true
  },
  {
    "name": "סעיד אלעביד",
    "idNumber": "55803985",
    "phone": "052-678-8304",
    "coordinationNumber": "48",
    "goodsType": "סלי מזון",
    "donorOrg": "GHF",
    "palletCount": "22",
    "passedAt": "13:46",
    "gatePassPrinted": true
  },
  {
    "name": "יוסי סעדון",
    "idNumber": "56673239",
    "phone": "053-770-5300",
    "coordinationNumber": "15",
    "goodsType": "מארזי מזון ",
    "donorOrg": "GHF",
    "palletCount": "22",
    "passedAt": "06:49",
    "gatePassPrinted": true
  },
  {
    "name": "שפיק אבו לטיף",
    "idNumber": "56961170",
    "phone": "053-757-8039",
    "coordinationNumber": "78",
    "goodsType": "שימורים - WCK",
    "donorOrg": "WCK",
    "palletCount": "22",
    "passedAt": "07:26",
    "gatePassPrinted": true
  },
  {
    "name": "זוארמי ברוך",
    "idNumber": "58693110",
    "phone": "058-542-1440",
    "coordinationNumber": "3",
    "goodsType": "מארזי מזון",
    "donorOrg": "GHF",
    "palletCount": "22",
    "passedAt": "12:18",
    "gatePassPrinted": true
  },
  {
    "name": "ואסף עזאיזה",
    "idNumber": "58987447",
    "phone": "050-525-8563",
    "coordinationNumber": "52",
    "goodsType": "מארזי מזון",
    "donorOrg": "GHF",
    "palletCount": "22",
    "passedAt": "11:30",
    "gatePassPrinted": true
  },
  {
    "name": "אבי לוי",
    "idNumber": "59043257",
    "phone": "054-777-9067",
    "coordinationNumber": "14",
    "goodsType": "סלי מזון",
    "donorOrg": "GHF",
    "palletCount": "22",
    "passedAt": "12:39",
    "gatePassPrinted": false
  },
  {
    "name": "אחמד קנואת",
    "idNumber": "59503912",
    "phone": "050-522-4781",
    "coordinationNumber": "84",
    "goodsType": "קמח - WFP",
    "donorOrg": "WFP",
    "palletCount": "18",
    "passedAt": "06:31",
    "gatePassPrinted": true
  },
  {
    "name": "אחמד חמאמרה",
    "idNumber": "59506410",
    "phone": "054-245-0706",
    "coordinationNumber": "85",
    "goodsType": "קמח - WFP",
    "donorOrg": "WFP",
    "palletCount": "18",
    "passedAt": "06:24",
    "gatePassPrinted": true
  },
  {
    "name": "מוחמד תופיק יוסף",
    "idNumber": "59552703",
    "phone": "050-554-5894",
    "coordinationNumber": "30",
    "goodsType": "מארזי מזון",
    "donorOrg": "GHF",
    "palletCount": "22",
    "passedAt": "14:17",
    "gatePassPrinted": true
  },
  {
    "name": "מוחמד ארשיד",
    "idNumber": "66521444",
    "phone": "053-431-8893",
    "coordinationNumber": "46",
    "goodsType": "מארזי מזון",
    "donorOrg": "GHF",
    "palletCount": "22",
    "passedAt": "14:16",
    "gatePassPrinted": true
  },
  {
    "name": "שאהר סנקרט",
    "idNumber": "80885817",
    "phone": "052-675-9625",
    "coordinationNumber": "75",
    "goodsType": "מזון",
    "donorOrg": "IHRC",
    "palletCount": "18",
    "passedAt": "07:40",
    "gatePassPrinted": true
  },
  {
    "name": "חסאם גאבר",
    "idNumber": "80959604",
    "phone": "052-548-6685",
    "coordinationNumber": "76",
    "goodsType": "סלי מזון ",
    "donorOrg": "IHRC",
    "palletCount": "18",
    "passedAt": "07:01",
    "gatePassPrinted": true
  },
  {
    "name": "ג'האד עווידה",
    "idNumber": "81022865",
    "phone": "050-546-4056",
    "coordinationNumber": "56",
    "goodsType": "סלי מזון",
    "donorOrg": "GHF",
    "palletCount": "22",
    "passedAt": "13:46",
    "gatePassPrinted": true
  },
  {
    "name": "פאדי סלהב",
    "idNumber": "81092769",
    "phone": "052-677-6624",
    "coordinationNumber": "87",
    "goodsType": "קמח - WFP",
    "donorOrg": "WFP",
    "palletCount": "18",
    "passedAt": "06:28",
    "gatePassPrinted": true
  },
  {
    "name": "דניאל ראשד",
    "idNumber": "200016426",
    "phone": "054-391-9404",
    "coordinationNumber": "29",
    "goodsType": "סלי מזון",
    "donorOrg": "GHF",
    "palletCount": "22",
    "passedAt": "14:16",
    "gatePassPrinted": true
  },
  {
    "name": "אחמד סלפיתי",
    "idNumber": "201350394",
    "phone": "050-777-8975",
    "coordinationNumber": "40",
    "goodsType": "סלי מזון",
    "donorOrg": "GHF",
    "palletCount": "22",
    "passedAt": "14:06",
    "gatePassPrinted": true
  },
  {
    "name": "מחמוד אבו דהש",
    "idNumber": "204229678",
    "phone": "054-323-7167",
    "coordinationNumber": "32",
    "goodsType": "סלי מזון",
    "donorOrg": "GHF",
    "palletCount": "22",
    "passedAt": "14:02",
    "gatePassPrinted": true
  },
  {
    "name": "האשם אבואישבה",
    "idNumber": "204329577",
    "phone": "055-662-2293",
    "coordinationNumber": "28",
    "goodsType": "מארזי מזון",
    "donorOrg": "GHF",
    "palletCount": "22",
    "passedAt": "14:07",
    "gatePassPrinted": true
  },
  {
    "name": "מור בן דוד",
    "idNumber": "204445092",
    "phone": "",
    "coordinationNumber": "60",
    "goodsType": "מארזי מזון",
    "donorOrg": "GHF",
    "palletCount": "22",
    "passedAt": "13:45",
    "gatePassPrinted": true
  },
  {
    "name": "היסם אבו זעילה",
    "idNumber": "204514483",
    "phone": "052-500-1492",
    "coordinationNumber": "7",
    "goodsType": "סלי מזון",
    "donorOrg": "GHF",
    "palletCount": "22",
    "passedAt": "13:08",
    "gatePassPrinted": false
  },
  {
    "name": "מוחמד אלגרנאוי",
    "idNumber": "204704928",
    "phone": "054-570-3657",
    "coordinationNumber": "79",
    "goodsType": "שימורים - WCK",
    "donorOrg": "WCK",
    "palletCount": "22",
    "passedAt": "07:25",
    "gatePassPrinted": true
  },
  {
    "name": "אמיר אלקרעאן",
    "idNumber": "206874745",
    "phone": "050-420-7736",
    "coordinationNumber": "19",
    "goodsType": "מארזי מזון",
    "donorOrg": "GHF",
    "palletCount": "22",
    "passedAt": "14:15",
    "gatePassPrinted": true
  },
  {
    "name": "וגוג אברהים",
    "idNumber": "207235532",
    "phone": "054-690-6220",
    "coordinationNumber": "20",
    "goodsType": "סלי מזון",
    "donorOrg": "GHF",
    "palletCount": "22",
    "passedAt": "14:20",
    "gatePassPrinted": true
  },
  {
    "name": "סולימאן גבועה",
    "idNumber": "208373324",
    "phone": "054-947-6099",
    "coordinationNumber": "27",
    "goodsType": "מארזי מזון",
    "donorOrg": "GHF",
    "palletCount": "22",
    "passedAt": "14:14",
    "gatePassPrinted": true
  },
  {
    "name": "יוסף אלעמראני",
    "idNumber": "209263680",
    "phone": "054-994-3232",
    "coordinationNumber": "23",
    "goodsType": "סלי מזון",
    "donorOrg": "GHF",
    "palletCount": "22",
    "passedAt": "14:22",
    "gatePassPrinted": true
  },
  {
    "name": "עלי אבו שריקה",
    "idNumber": "211445473",
    "phone": "050-386-8939",
    "coordinationNumber": "35",
    "goodsType": "מארזי מזון",
    "donorOrg": "GHF",
    "palletCount": "22",
    "passedAt": "14:18",
    "gatePassPrinted": true
  },
  {
    "name": "מוחמד אבו רכבה",
    "idNumber": "212650097",
    "phone": "054-334-5935",
    "coordinationNumber": "25",
    "goodsType": "סלי מזון",
    "donorOrg": "GHF",
    "palletCount": "22",
    "passedAt": "14:22",
    "gatePassPrinted": true
  },
  {
    "name": "שחר משה",
    "idNumber": "295860050",
    "phone": "053-220-4264",
    "coordinationNumber": "81",
    "goodsType": "שעועית - WCK",
    "donorOrg": "WCK",
    "palletCount": "22",
    "passedAt": "09:38",
    "gatePassPrinted": true
  },
  {
    "name": "מוסא אבו האני",
    "idNumber": "300127073",
    "phone": "054-640-0498",
    "coordinationNumber": "90",
    "goodsType": "קמח - WFP",
    "donorOrg": "WFP",
    "palletCount": "18",
    "passedAt": "09:21",
    "gatePassPrinted": true
  },
  {
    "name": "אמיר חואגרה",
    "idNumber": "300127396",
    "phone": "052-212-1262",
    "coordinationNumber": "39",
    "goodsType": "מארזי מזון",
    "donorOrg": "GHF",
    "palletCount": "22",
    "passedAt": "14:19",
    "gatePassPrinted": false
  },
  {
    "name": "מוסטפא איכתילאת",
    "idNumber": "300698578",
    "phone": "050-295-4555",
    "coordinationNumber": "33",
    "goodsType": "מארזי מזון",
    "donorOrg": "GHF",
    "palletCount": "22",
    "passedAt": "14:09",
    "gatePassPrinted": true
  },
  {
    "name": "אלזברגה עגל",
    "idNumber": "301110250",
    "phone": "050-441-1171",
    "coordinationNumber": "6",
    "goodsType": "סלי מזון",
    "donorOrg": "GHF",
    "palletCount": "22",
    "passedAt": "09:51",
    "gatePassPrinted": true
  },
  {
    "name": "זייד סבאח",
    "idNumber": "303117535",
    "phone": "054-749-5910",
    "coordinationNumber": "38",
    "goodsType": "מארזי מזון",
    "donorOrg": "GHF",
    "palletCount": "22",
    "passedAt": "14:08",
    "gatePassPrinted": true
  },
  {
    "name": "איגור אליסטרטוב",
    "idNumber": "303479430",
    "phone": "053-239-2871",
    "coordinationNumber": "11",
    "goodsType": "סלי מזון",
    "donorOrg": "GHF",
    "palletCount": "22",
    "passedAt": "11:30",
    "gatePassPrinted": true
  },
  {
    "name": "איגור אליסטרטוב",
    "idNumber": "303479430",
    "phone": "053-239-2871",
    "coordinationNumber": "69",
    "goodsType": "מארזי מזון",
    "donorOrg": "GHF",
    "palletCount": "22",
    "passedAt": "13:42",
    "gatePassPrinted": true
  },
  {
    "name": "עמאד אלאצלע",
    "idNumber": "305531428",
    "phone": "053-224-6422",
    "coordinationNumber": "58",
    "goodsType": "מארזי מזון ",
    "donorOrg": "GHF",
    "palletCount": "22",
    "passedAt": "11:32",
    "gatePassPrinted": true
  },
  {
    "name": "אעסם אלגלמאוי",
    "idNumber": "307895904",
    "phone": "052-302-5514",
    "coordinationNumber": "49",
    "goodsType": "סלי מזון ",
    "donorOrg": "GHF",
    "palletCount": "22",
    "passedAt": "11:32",
    "gatePassPrinted": true
  },
  {
    "name": "מוחמד אבו עצא",
    "idNumber": "307903922",
    "phone": "050-767-7002",
    "coordinationNumber": "24",
    "goodsType": "סלי מזון",
    "donorOrg": "GHF",
    "palletCount": "22",
    "passedAt": "14:13",
    "gatePassPrinted": true
  },
  {
    "name": "איגור ברוסילובסקי",
    "idNumber": "309069136",
    "phone": "053-986-0608",
    "coordinationNumber": "67",
    "goodsType": "מארזי מזון",
    "donorOrg": "GHF",
    "palletCount": "22",
    "passedAt": "13:48",
    "gatePassPrinted": true
  },
  {
    "name": "זאב אגרנובסקי",
    "idNumber": "311926554",
    "phone": "052-648-2248",
    "coordinationNumber": "13",
    "goodsType": "סלי מזון",
    "donorOrg": "GHF",
    "palletCount": "22",
    "passedAt": "07:13",
    "gatePassPrinted": true
  },
  {
    "name": "זאב אגרנובסקי",
    "idNumber": "311926554",
    "phone": "052-648-2248",
    "coordinationNumber": "95",
    "goodsType": "קמח - WFP",
    "donorOrg": "WFP",
    "palletCount": "18",
    "passedAt": "11:45",
    "gatePassPrinted": false
  },
  {
    "name": "גרמן בבג'ב",
    "idNumber": "312940950",
    "phone": "054-771-9981",
    "coordinationNumber": "62",
    "goodsType": "מארזי מזון",
    "donorOrg": "GHF",
    "palletCount": "22",
    "passedAt": "13:47",
    "gatePassPrinted": true
  },
  {
    "name": "ראיד סקיק",
    "idNumber": "313185035",
    "phone": "050-740-3577",
    "coordinationNumber": "65",
    "goodsType": "מארזי מזון",
    "donorOrg": "GHF",
    "palletCount": "22",
    "passedAt": "13:45",
    "gatePassPrinted": true
  },
  {
    "name": "מהדי מועיין מוחמד",
    "idNumber": "313390817",
    "phone": "050-988-3350",
    "coordinationNumber": "54",
    "goodsType": "סלי מזון",
    "donorOrg": "GHF",
    "palletCount": "22",
    "passedAt": "13:49",
    "gatePassPrinted": true
  },
  {
    "name": "מהדי מועיין מוחמד",
    "idNumber": "313390817",
    "phone": "050-988-3350",
    "coordinationNumber": "83",
    "goodsType": "קמח - WFP",
    "donorOrg": "WFP",
    "palletCount": "18",
    "passedAt": "06:30",
    "gatePassPrinted": true
  },
  {
    "name": "אבראהים עומרי",
    "idNumber": "315889451",
    "phone": "054-264-8844",
    "coordinationNumber": "45",
    "goodsType": "סלי מזון",
    "donorOrg": "GHF",
    "palletCount": "22",
    "passedAt": "14:05",
    "gatePassPrinted": true
  },
  {
    "name": "מוחמד אימטיראת",
    "idNumber": "316001965",
    "phone": "050-240-0410",
    "coordinationNumber": "37",
    "goodsType": "סלי מזון",
    "donorOrg": "GHF",
    "palletCount": "22",
    "passedAt": "14:20",
    "gatePassPrinted": true
  },
  {
    "name": "אימן גבועה",
    "idNumber": "316177039",
    "phone": "050-892-8230",
    "coordinationNumber": "18",
    "goodsType": "מארזי מזון",
    "donorOrg": "GHF",
    "palletCount": "22",
    "passedAt": "14:14",
    "gatePassPrinted": true
  },
  {
    "name": "ענאן סעאידה",
    "idNumber": "316379411",
    "phone": "054-335-6118",
    "coordinationNumber": "43",
    "goodsType": "סלי מזון",
    "donorOrg": "GHF",
    "palletCount": "22",
    "passedAt": "14:05",
    "gatePassPrinted": true
  },
  {
    "name": "טאמר אלמחדי",
    "idNumber": "316587211",
    "phone": "054-223-2956",
    "coordinationNumber": "21",
    "goodsType": "מארזי מזון",
    "donorOrg": "GHF",
    "palletCount": "22",
    "passedAt": "14:10",
    "gatePassPrinted": true
  },
  {
    "name": "ולדימיר קורו",
    "idNumber": "320534100",
    "phone": "052-860-7023",
    "coordinationNumber": "17",
    "goodsType": "סלי מזון",
    "donorOrg": "GHF",
    "palletCount": "22",
    "passedAt": "08:51",
    "gatePassPrinted": true
  },
  {
    "name": "ולדימיר קורו",
    "idNumber": "320534100",
    "phone": "052-860-7023",
    "coordinationNumber": "97",
    "goodsType": "קמח - WFP",
    "donorOrg": "WFP",
    "palletCount": "18",
    "passedAt": "07:56",
    "gatePassPrinted": true
  },
  {
    "name": "גנאדי ניקולייב",
    "idNumber": "321778219",
    "phone": "054-486-2044",
    "coordinationNumber": "71",
    "goodsType": "סלי מזון",
    "donorOrg": "GHF",
    "palletCount": "22",
    "passedAt": "11:27",
    "gatePassPrinted": true
  },
  {
    "name": "באסל עוידה",
    "idNumber": "322241332",
    "phone": "050-430-2396",
    "coordinationNumber": "34",
    "goodsType": "סלי מזון",
    "donorOrg": "GHF",
    "palletCount": "22",
    "passedAt": "14:16",
    "gatePassPrinted": true
  },
  {
    "name": "אקרם אלהוזייל",
    "idNumber": "322860206",
    "phone": "050-834-6397",
    "coordinationNumber": "72",
    "goodsType": "מארזי מזון ",
    "donorOrg": "GHF",
    "palletCount": "21",
    "passedAt": "11:33",
    "gatePassPrinted": true
  },
  {
    "name": "ענאמי עזאלדין",
    "idNumber": "326009347",
    "phone": "052-796-1359",
    "coordinationNumber": "26",
    "goodsType": "סלי מזון",
    "donorOrg": "GHF",
    "palletCount": "22",
    "passedAt": "14:21",
    "gatePassPrinted": true
  },
  {
    "name": "שרון באני",
    "idNumber": "25454323",
    "phone": "054-233-0023",
    "coordinationNumber": "2",
    "goodsType": "סלי מזון",
    "donorOrg": "GHF",
    "palletCount": "22",
    "passedAt": "11:18",
    "gatePassPrinted": true
  },
  {
    "name": "מיכאל קריצנקו",
    "idNumber": "32329708",
    "phone": "054-639-6760",
    "coordinationNumber": "88",
    "goodsType": "קמח - WFP",
    "donorOrg": "WFP",
    "palletCount": "18",
    "passedAt": "06:25",
    "gatePassPrinted": true
  },
  {
    "name": "אדם אלעביד",
    "idNumber": "316179837",
    "phone": "-",
    "coordinationNumber": "98",
    "goodsType": "מארזי מזון",
    "donorOrg": "GHF",
    "palletCount": "22",
    "passedAt": "11:26",
    "gatePassPrinted": true
  }
]